{
  "puri":[
    {
      "hotel":"XYZ",
      "price":1200,
      "type":"P",
      "id":"10001"
    },
    {
      "hotel":"XYZ",
      "price":1200,
      "type":"P",
      "id":"10001"
    },
    {
      "hotel":"XYZ",
      "price":1200,
      "type":"P",
      "id":"10001"
    },
    {
      "hotel":"XYZ",
      "price":1200,
      "type":"P",
      "id":"10001"
    },{
      "hotel":"XYZ",
      "price":1200,
      "type":"P",
      "id":"10001"
    },{
      "hotel":"XYZ",
      "price":1200,
      "type":"P",
      "id":"10001"
    },
    {
      "hotel":"XYZ",
      "price":1200,
      "type":"P",
      "id":"10001"
    },
    {
      "hotel":"XYZ",
      "price":1200,
      "type":"P",
      "id":"10001"
    },
    {
      "hotel":"XYZ",
      "price":1200,
      "type":"P",
      "id":"10001"
    },
    {
      "hotel":"XYZ",
      "price":1200,
      "type":"P",
      "id":"10001"
    }
  ]
}